python_pae/__init__.py
python_pae/abstract.py
python_pae/encode.py
python_pae/number.py
python_pae/pae_types.py
python_pae-0.1.0.dist-info/LICENSE
python_pae-0.1.0.dist-info/WHEEL
python_pae-0.1.0.dist-info/METADATA
python_pae-0.1.0.dist-info/RECORD
