Metadata-Version: 2.1
Name: python-pae
Version: 0.1.0
Summary: Pre-authentication encoding (PAE) implementation in Python
Home-page: https://github.com/MatthiasValvekens/python-pae
License: MIT
Author: Matthias Valvekens
Author-email: dev@mvalvekens.be
Requires-Python: >=3.7,<4.0
Classifier: Development Status :: 3 - Alpha
Classifier: Intended Audience :: Developers
Classifier: License :: OSI Approved :: MIT License
Classifier: Programming Language :: Python :: 3
Classifier: Programming Language :: Python :: 3.7
Classifier: Programming Language :: Python :: 3.8
Classifier: Programming Language :: Python :: 3.9
Classifier: Topic :: Security :: Cryptography
Classifier: Topic :: Software Development :: Libraries :: Python Modules
Project-URL: Documentation, https://python-pae.readthedocs.io/
Project-URL: Repository, https://github.com/MatthiasValvekens/python-pae
